{
  "resourceType": "CodeSystem",
  "id": "delivery-purpose",
  "url": "https://bind.codes/delivery-purpose",
  "name": "DeliveryPurpose",
  "title": "Delivery Purpose",
  "status": "draft",
  "language": "en",
  "description": "Delivery Purpose codes for insurance operations.",
  "concept": [
    {
      "code": "N",
      "display": "No Delivery",
      "definition": "No Delivery — delivery purpose code.",
      "designation": [
        {
          "language": "fr-CA",
          "value": "Aucune livraison"
        }
      ]
    },
    {
      "code": "O",
      "display": "Other",
      "definition": "Other — delivery purpose code.",
      "designation": [
        {
          "language": "fr-CA",
          "value": "Autre"
        }
      ]
    },
    {
      "code": "R",
      "display": "Retail Delivery",
      "definition": "Retail Delivery — delivery purpose code.",
      "designation": [
        {
          "language": "fr-CA",
          "value": "Livraison au détail"
        }
      ]
    },
    {
      "code": "W",
      "display": "Wholesale Delivery",
      "definition": "Wholesale Delivery — delivery purpose code.",
      "designation": [
        {
          "language": "fr-CA",
          "value": "Livraison vente en gros"
        }
      ]
    },
    {
      "code": "M",
      "display": "Moving or Storage",
      "definition": "Moving or Storage — delivery purpose code.",
      "designation": [
        {
          "language": "fr-CA",
          "value": "Déménagement ou Stockage"
        }
      ]
    }
  ]
}
