{
  "resourceType": "CodeSystem",
  "id": "use",
  "url": "https://bind.codes/use",
  "name": "Use",
  "title": "Use",
  "status": "draft",
  "language": "en",
  "description": "Use codes for insurance operations.",
  "concept": [
    {
      "code": "personal-use",
      "display": "Personal Use",
      "definition": "Personal Use — use code.",
      "designation": [
        {
          "language": "fr-CA",
          "value": "Usage personnel"
        }
      ]
    },
    {
      "code": "business-use",
      "display": "Business Use",
      "definition": "Business Use — use code.",
      "designation": [
        {
          "language": "fr-CA",
          "value": "Activités professionnelles"
        }
      ]
    },
    {
      "code": "other",
      "display": "Other",
      "definition": "Other — use code.",
      "designation": [
        {
          "language": "fr-CA",
          "value": "Autre"
        }
      ]
    },
    {
      "code": "AUX",
      "display": "Auxiliary",
      "definition": "Auxiliary — use code.",
      "designation": [
        {
          "language": "fr-CA",
          "value": "Secondaire"
        }
      ]
    },
    {
      "code": "P",
      "display": "Pleasure",
      "definition": "Pleasure — use code.",
      "designation": [
        {
          "language": "fr-CA",
          "value": "Usage récréatif, promenade"
        }
      ]
    },
    {
      "code": "PRI",
      "display": "Primary",
      "definition": "Primary — use code.",
      "designation": [
        {
          "language": "fr-CA",
          "value": "Principal"
        }
      ]
    }
  ]
}
